Metadata-Version: 2.1
Name: ifx-jama-api
Version: 0.0.1
Summary: A package that allows to create TCs for every ReQ automatically and more.
Home-page: https://bitbucket.vih.infineon.com/users/trinkler/repos/jama-package/browse
Author: Raphael Trinkler
Maintainer: Raphael Trinkler
Maintainer-email: raphael.trinkler@infineon.com
License: Proprietary
Project-URL: Documentation, https://bitbucket.vih.infineon.com/users/trinkler/repos/jama-package/browse/README.md
Platform: any
Classifier: Operating System :: OS Independent
Classifier: Programming Language :: Python :: 3
Classifier: License :: Other/Proprietary License
Classifier: Topic :: Database :: Front-Ends
Classifier: Topic :: Software Development :: Libraries
Requires-Python: >=3.9
License-File: LICENSE.txt
